<annotation>
	<folder></folder>
	<filename>0320b561562e469c_jpg.rf.6a572781533194fb13264ce962e4b790.jpg</filename>
	<path>0320b561562e469c_jpg.rf.6a572781533194fb13264ce962e4b790.jpg</path>
	<source>
		<database>roboflow.ai</database>
	</source>
	<size>
		<width>300</width>
		<height>300</height>
		<depth>3</depth>
	</size>
	<segmented>0</segmented>
	<object>
		<name>Vehicle-registration-plate</name>
		<pose>Unspecified</pose>
		<truncated>0</truncated>
		<difficult>0</difficult>
		<occluded>0</occluded>
		<bndbox>
			<xmin>196</xmin>
			<xmax>208</xmax>
			<ymin>100</ymin>
			<ymax>105</ymax>
		</bndbox>
	</object>
</annotation>
