<annotation>
	<folder></folder>
	<filename>1d542803f9e35f52_jpg.rf.1455587ec0ec812e3b9927711c3d5023.jpg</filename>
	<path>1d542803f9e35f52_jpg.rf.1455587ec0ec812e3b9927711c3d5023.jpg</path>
	<source>
		<database>roboflow.ai</database>
	</source>
	<size>
		<width>300</width>
		<height>300</height>
		<depth>3</depth>
	</size>
	<segmented>0</segmented>
	<object>
		<name>Vehicle-registration-plate</name>
		<pose>Unspecified</pose>
		<truncated>0</truncated>
		<difficult>0</difficult>
		<occluded>0</occluded>
		<bndbox>
			<xmin>186</xmin>
			<xmax>253</xmax>
			<ymin>226</ymin>
			<ymax>248</ymax>
		</bndbox>
	</object>
</annotation>
