<annotation>
	<folder></folder>
	<filename>362373a86934dd4f_jpg.rf.9a320997a51749a9cbb6736cd4fb9202.jpg</filename>
	<path>362373a86934dd4f_jpg.rf.9a320997a51749a9cbb6736cd4fb9202.jpg</path>
	<source>
		<database>roboflow.ai</database>
	</source>
	<size>
		<width>300</width>
		<height>300</height>
		<depth>3</depth>
	</size>
	<segmented>0</segmented>
	<object>
		<name>Vehicle-registration-plate</name>
		<pose>Unspecified</pose>
		<truncated>0</truncated>
		<difficult>0</difficult>
		<occluded>0</occluded>
		<bndbox>
			<xmin>67</xmin>
			<xmax>81</xmax>
			<ymin>120</ymin>
			<ymax>132</ymax>
		</bndbox>
	</object>
	<object>
		<name>Vehicle-registration-plate</name>
		<pose>Unspecified</pose>
		<truncated>0</truncated>
		<difficult>0</difficult>
		<occluded>0</occluded>
		<bndbox>
			<xmin>244</xmin>
			<xmax>257</xmax>
			<ymin>140</ymin>
			<ymax>155</ymax>
		</bndbox>
	</object>
</annotation>
