<annotation>
	<folder></folder>
	<filename>60c3daa31e1c7cf4_jpg.rf.554a0c9f48320c3d20d93489cb6717f7.jpg</filename>
	<path>60c3daa31e1c7cf4_jpg.rf.554a0c9f48320c3d20d93489cb6717f7.jpg</path>
	<source>
		<database>roboflow.ai</database>
	</source>
	<size>
		<width>300</width>
		<height>300</height>
		<depth>3</depth>
	</size>
	<segmented>0</segmented>
	<object>
		<name>Vehicle-registration-plate</name>
		<pose>Unspecified</pose>
		<truncated>0</truncated>
		<difficult>0</difficult>
		<occluded>0</occluded>
		<bndbox>
			<xmin>128</xmin>
			<xmax>172</xmax>
			<ymin>223</ymin>
			<ymax>237</ymax>
		</bndbox>
	</object>
</annotation>
