<annotation>
	<folder></folder>
	<filename>72e091be8b5712d3_jpg.rf.4a949b80327520965dedc3a531f0699b.jpg</filename>
	<path>72e091be8b5712d3_jpg.rf.4a949b80327520965dedc3a531f0699b.jpg</path>
	<source>
		<database>roboflow.ai</database>
	</source>
	<size>
		<width>300</width>
		<height>300</height>
		<depth>3</depth>
	</size>
	<segmented>0</segmented>
	<object>
		<name>Vehicle-registration-plate</name>
		<pose>Unspecified</pose>
		<truncated>0</truncated>
		<difficult>0</difficult>
		<occluded>0</occluded>
		<bndbox>
			<xmin>39</xmin>
			<xmax>56</xmax>
			<ymin>169</ymin>
			<ymax>189</ymax>
		</bndbox>
	</object>
</annotation>
