<annotation>
	<folder></folder>
	<filename>8e7ecbc0baae4807_jpg.rf.a83c875b81d7b2d49dc7d8568267a3e5.jpg</filename>
	<path>8e7ecbc0baae4807_jpg.rf.a83c875b81d7b2d49dc7d8568267a3e5.jpg</path>
	<source>
		<database>roboflow.ai</database>
	</source>
	<size>
		<width>300</width>
		<height>300</height>
		<depth>3</depth>
	</size>
	<segmented>0</segmented>
	<object>
		<name>Vehicle-registration-plate</name>
		<pose>Unspecified</pose>
		<truncated>0</truncated>
		<difficult>0</difficult>
		<occluded>0</occluded>
		<bndbox>
			<xmin>71</xmin>
			<xmax>75</xmax>
			<ymin>204</ymin>
			<ymax>208</ymax>
		</bndbox>
	</object>
	<object>
		<name>Vehicle-registration-plate</name>
		<pose>Unspecified</pose>
		<truncated>0</truncated>
		<difficult>0</difficult>
		<occluded>0</occluded>
		<bndbox>
			<xmin>133</xmin>
			<xmax>139</xmax>
			<ymin>200</ymin>
			<ymax>204</ymax>
		</bndbox>
	</object>
</annotation>
