<annotation><folder>open_images_volume</folder><filename>515dfd3f0992a44d.jpg</filename><path>/mnt/open_images_volume/515dfd3f0992a44d.jpg</path><source><database>Unknown</database></source><size><width>1024</width><height>768</height><depth>3</depth></size><segmented>0</segmented><object><name>Vehicle registration plate</name><pose>Unspecified</pose><truncated>0</truncated><difficult>0</difficult><bndbox><xmin>97</xmin><ymin>451</ymin><xmax>131</xmax><ymax>518</ymax></bndbox></object></annotation>