<annotation><folder>open_images_volume</folder><filename>99504a60b89185e5.jpg</filename><path>/mnt/open_images_volume/99504a60b89185e5.jpg</path><source><database>Unknown</database></source><size><width>1024</width><height>576</height><depth>3</depth></size><segmented>0</segmented><object><name>Vehicle registration plate</name><pose>Unspecified</pose><truncated>0</truncated><difficult>0</difficult><bndbox><xmin>774</xmin><ymin>225</ymin><xmax>858</xmax><ymax>289</ymax></bndbox></object></annotation>