<annotation><folder>open_images_volume</folder><filename>f23c59307587e6a4.jpg</filename><path>/mnt/open_images_volume/f23c59307587e6a4.jpg</path><source><database>Unknown</database></source><size><width>1024</width><height>682</height><depth>3</depth></size><segmented>0</segmented><object><name>Vehicle registration plate</name><pose>Unspecified</pose><truncated>0</truncated><difficult>0</difficult><bndbox><xmin>843</xmin><ymin>293</ymin><xmax>918</xmax><ymax>341</ymax></bndbox></object></annotation>