<annotation><folder>open_images_volume</folder><filename>ff74617a514d2b82.jpg</filename><path>/mnt/open_images_volume/ff74617a514d2b82.jpg</path><source><database>Unknown</database></source><size><width>768</width><height>1024</height><depth>3</depth></size><segmented>0</segmented><object><name>Vehicle registration plate</name><pose>Unspecified</pose><truncated>0</truncated><difficult>0</difficult><bndbox><xmin>135</xmin><ymin>564</ymin><xmax>273</xmax><ymax>611</ymax></bndbox></object></annotation>